fools/__init__.py
fools/extractor.py
fools/fsender.py
fools/imageSeparator.py
fools/main.py
fools/renamer.py
fools/surrounder.py
fools/vidmaker.py
fools/ytdownloader.py
ftools/__init__.py
ftools/extractor.py
ftools/fsender.py
ftools/imageSeparator.py
ftools/main.py
ftools/renamer.py
ftools/surrounder.py
ftools/vidmaker.py
ftools/ytdownloader.py
ftools/ytinstaller.py
fools-1.12.dist-info/METADATA
fools-1.12.dist-info/WHEEL
fools-1.12.dist-info/entry_points.txt
fools-1.12.dist-info/top_level.txt
fools-1.12.dist-info/RECORD
